MANIFEST.in
README.md
README.rst
setup.cfg
setup.py
Solgema/__init__.py
Solgema.ContextualContentMenu.egg-info/PKG-INFO
Solgema.ContextualContentMenu.egg-info/SOURCES.txt
Solgema.ContextualContentMenu.egg-info/dependency_links.txt
Solgema.ContextualContentMenu.egg-info/entry_points.txt
Solgema.ContextualContentMenu.egg-info/namespace_packages.txt
Solgema.ContextualContentMenu.egg-info/not-zip-safe
Solgema.ContextualContentMenu.egg-info/requires.txt
Solgema.ContextualContentMenu.egg-info/top_level.txt
Solgema/ContextualContentMenu/__init__.py
Solgema/ContextualContentMenu/config.py
Solgema/ContextualContentMenu/configure.zcml
Solgema/ContextualContentMenu/interfaces.py
Solgema/ContextualContentMenu/profiles.zcml
Solgema/ContextualContentMenu/setuphandlers.py
Solgema/ContextualContentMenu/skins.zcml
Solgema/ContextualContentMenu/views.py
Solgema/ContextualContentMenu/profiles/default/browserlayer.xml
Solgema/ContextualContentMenu/profiles/default/cssregistry.xml
Solgema/ContextualContentMenu/profiles/default/import_steps.xml
Solgema/ContextualContentMenu/profiles/default/jsregistry.xml
Solgema/ContextualContentMenu/profiles/default/metadata.xml
Solgema/ContextualContentMenu/profiles/default/skins.xml
Solgema/ContextualContentMenu/profiles/default/solgemacontextualcontentmenu_various.txt
Solgema/ContextualContentMenu/profiles/uninstall/cssregistry.xml
Solgema/ContextualContentMenu/profiles/uninstall/jsregistry.xml
Solgema/ContextualContentMenu/profiles/uninstall/metadata.xml
Solgema/ContextualContentMenu/profiles/uninstall/skins.xml
Solgema/ContextualContentMenu/skins/ContextualContentMenu/contextualContentMenu.pt
Solgema/ContextualContentMenu/skins/ContextualContentMenu/solgema_contextualcontentmenu.css
Solgema/ContextualContentMenu/skins/ContextualContentMenu/solgema_contextualcontentmenu.js
Solgema/ContextualContentMenu/viewlets/__init__.py
Solgema/ContextualContentMenu/viewlets/common.py
Solgema/ContextualContentMenu/viewlets/configure.zcml
Solgema/ContextualContentMenu/viewlets/contentactions.pt
docs/HISTORY.rst
docs/INSTALL.rst
docs/LICENSE.GPL
docs/LICENSE.rst