Metadata-Version: 1.1
Name: Solgema.ContextualContentMenu
Version: 0.3
Summary: Solgema Contextual Content Menu
Home-page: http://www.martronic.ch/Solgema/plone_products/solgema_contextualcontentmenu
Author: Martronic SA
Author-email: martronic@martronic.ch
License: GPL
Keywords: Solgema,menu,javascript menu
Platform: UNKNOWN
Classifier: Framework :: Plone
Classifier: Programming Language :: Python
Classifier: Topic :: Software Development :: Libraries :: Python Modules
